opticalflowleo/__init__.py
opticalflowleo/cld_mask_cth.py
opticalflowleo/output.py
opticalflowleo/plot.py
opticalflowleo/polar_RAFT_runner.py
opticalflowleo/raft_inference.py
opticalflowleo/resample.py
opticalflowleo/ssec_rink_util/.git
opticalflowleo/ssec_rink_util/README.md
opticalflowleo/ssec_rink_util/__init__.py
opticalflowleo/ssec_rink_util/files.py
opticalflowleo/ssec_rink_util/util.py
opticalflowleo/windflow_light/.git
opticalflowleo/windflow_light/LICENSE
opticalflowleo/windflow_light/README.md
opticalflowleo/windflow_light/__init__.py
opticalflowleo/windflow_light/model_weights/windflow.raft.pth.tar
opticalflowleo/windflow_light/windflow/__init__.py
opticalflowleo/windflow_light/windflow/inference_flows.py
opticalflowleo/windflow_light/windflow/datasets/__init__.py
opticalflowleo/windflow_light/windflow/datasets/goesr.py
opticalflowleo/windflow_light/windflow/datasets/preprocess.py
opticalflowleo/windflow_light/windflow/datasets/stats.py
opticalflowleo/windflow_light/windflow/datasets/utils.py
opticalflowleo/windflow_light/windflow/networks/__init__.py
opticalflowleo/windflow_light/windflow/networks/models.py
opticalflowleo/windflow_light/windflow/networks/warper.py
opticalflowleo/windflow_light/windflow/networks/raft/__init__.py
opticalflowleo/windflow_light/windflow/networks/raft/corr.py
opticalflowleo/windflow_light/windflow/networks/raft/extractor.py
opticalflowleo/windflow_light/windflow/networks/raft/raft.py
opticalflowleo/windflow_light/windflow/networks/raft/update.py
opticalflowleo/windflow_light/windflow/networks/raft/utils/__init__.py
opticalflowleo/windflow_light/windflow/networks/raft/utils/augmentor.py
opticalflowleo/windflow_light/windflow/networks/raft/utils/flow_viz.py
opticalflowleo/windflow_light/windflow/networks/raft/utils/frame_utils.py
opticalflowleo/windflow_light/windflow/networks/raft/utils/utils.py
opticalflowleo-0.9.5.dist-info/METADATA
opticalflowleo-0.9.5.dist-info/WHEEL
opticalflowleo-0.9.5.dist-info/licenses/LICENSE
opticalflowleo-0.9.5.dist-info/RECORD
