Metadata-Version: 2.3
Name: opticalflowleo
Version: 0.9.5
Summary: Optical Flow derived winds from overlapping LEO granules
Project-URL: Homepage, https://gitlab.ssec.wisc.edu/rink/windflow_leo
Author-email: "T.Rink" <rink@ssec.wisc.edu>
License-File: LICENSE
Classifier: License :: OSI Approved :: MIT License
Classifier: Operating System :: OS Independent
Classifier: Programming Language :: Python :: 3
Requires-Python: >=3.8
